emodeconnection/__init__.py
emodeconnection/__main__.py
emodeconnection/constants.py
emodeconnection/emodeclient.py
emodeconnection/emodeconnection.py
emodeconnection/eph_utils.py
emodeconnection/file_utils.py
emodeconnection/types.py
emodeconnection-1.1.2.dist-info/METADATA
emodeconnection-1.1.2.dist-info/WHEEL
emodeconnection-1.1.2.dist-info/licenses/LICENSE
emodeconnection-1.1.2.dist-info/RECORD
